djbackoffice/__init__.py
djbackoffice/apps.py
djbackoffice/core.py
djbackoffice/decorators.py
djbackoffice/mixin.py
djbackoffice/models.py
djbackoffice/settings.py
djbackoffice/tables.py
djbackoffice/tests.py
djbackoffice/utils.py
djbackoffice/views.py
djbackoffice/migrations/__init__.py
django_backoffice_dashboard_alpha-0.0.1a1.dist-info/LICENSE
django_backoffice_dashboard_alpha-0.0.1a1.dist-info/METADATA
django_backoffice_dashboard_alpha-0.0.1a1.dist-info/WHEEL
django_backoffice_dashboard_alpha-0.0.1a1.dist-info/top_level.txt
django_backoffice_dashboard_alpha-0.0.1a1.dist-info/RECORD
